vlpaket/__init__.py
vlpaket/pechascript.py
vlpaket-0.1.0.dist-info/METADATA
vlpaket-0.1.0.dist-info/WHEEL
vlpaket-0.1.0.dist-info/top_level.txt
vlpaket-0.1.0.dist-info/RECORD
