Metadata-Version: 2.1
Name: vlpaket
Version: 0.1.0
Summary: Best package
Author: vadlap
Author-email: vadlaped@gmail.com
